search_that_hash/__init__.py
search_that_hash/__main__.py
search_that_hash/api.py
search_that_hash/config_object.py
search_that_hash/cracker/__init__.py
search_that_hash/cracker/cracking.py
search_that_hash/cracker/fast_mode_mod/__init__.py
search_that_hash/cracker/fast_mode_mod/runner.py
search_that_hash/cracker/greppable_mode_mod/__init__.py
search_that_hash/cracker/greppable_mode_mod/runner.py
search_that_hash/cracker/handler.py
search_that_hash/cracker/offline_mod/__init__.py
search_that_hash/cracker/offline_mod/hashcat.py
search_that_hash/cracker/offline_mod/john.py
search_that_hash/cracker/offline_mod/offline.py
search_that_hash/cracker/online_mod/__init__.py
search_that_hash/cracker/online_mod/online.py
search_that_hash/cracker/sth_mod/__init__.py
search_that_hash/cracker/sth_mod/sth.py
search_that_hash/printing.py
search_that_hash-0.2.8.dist-info/entry_points.txt
search_that_hash-0.2.8.dist-info/LICENSE
search_that_hash-0.2.8.dist-info/WHEEL
search_that_hash-0.2.8.dist-info/METADATA
search_that_hash-0.2.8.dist-info/RECORD
