Metadata-Version: 2.1
Name: search-that-hash
Version: 0.2.8
Summary: Search hashes quickly before cracking them
License: GPL-3.0-or-later
Author: brandon
Author-email: brandon@skerritt.blog
Requires-Python: >=3.7,<4.0
Classifier: License :: OSI Approved :: GNU General Public License v3 or later (GPLv3+)
Classifier: Programming Language :: Python :: 3
Classifier: Programming Language :: Python :: 3.7
Classifier: Programming Language :: Python :: 3.8
Classifier: Programming Language :: Python :: 3.9
Requires-Dist: appdirs (>=1.4.4,<2.0.0)
Requires-Dist: click (>=7.1.2,<8.0.0)
Requires-Dist: cloudscraper (>=1.2.56,<2.0.0)
Requires-Dist: coloredlogs (>=15.0,<16.0)
Requires-Dist: loguru (>=0.5.3,<0.6.0)
Requires-Dist: name-that-hash (>=1.1.6,<2.0.0)
Requires-Dist: requests (>=2.25.1,<3.0.0)
Requires-Dist: rich (>=9.12.2,<10.0.0)
Requires-Dist: toml (>=0.10.2,<0.11.0)
